svgtrace/__init__.py
svgtrace/imagetracer.html
svgtrace/imagetracer.js
svgtrace-2023.1.dist-info/LICENSE.md
svgtrace-2023.1.dist-info/METADATA
svgtrace-2023.1.dist-info/WHEEL
svgtrace-2023.1.dist-info/RECORD
