Metadata-Version: 2.1
Name: svgtrace
Version: 2023.1
Summary: Leverage playwright and the imagetrace.js library to trace a bitmap to svg in python
Home-page: https://github.com/FHPythonUtils/SvgTrace
License: MIT
Author: FredHappyface
Requires-Python: >=3.9,<4.0
Classifier: Development Status :: 5 - Production/Stable
Classifier: Intended Audience :: Developers
Classifier: Intended Audience :: Education
Classifier: License :: OSI Approved :: MIT License
Classifier: Natural Language :: English
Classifier: Operating System :: OS Independent
Classifier: Programming Language :: Python :: 3
Classifier: Programming Language :: Python :: 3.9
Classifier: Programming Language :: Python :: 3.10
Classifier: Programming Language :: Python :: 3.11
Classifier: Programming Language :: Python :: Implementation :: CPython
Classifier: Topic :: Multimedia :: Graphics
Classifier: Topic :: Software Development :: Libraries :: Python Modules
Classifier: Topic :: Utilities
Requires-Dist: install-playwright (>=0.0.0,<2)
Requires-Dist: numpy (>=1.25.0,<2)
Requires-Dist: pillow (>=9.5.0,<10)
Requires-Dist: playwright (>=1.35.0,<2)
Requires-Dist: scikit-image (>=0.21.0,<2)
Project-URL: Documentation, https://github.com/FHPythonUtils/SvgTrace/blob/master/README.md
Project-URL: Repository, https://github.com/FHPythonUtils/SvgTrace
